insta_hashtag_crawler/__init__.py
insta_hashtag_crawler/command.py
insta_hashtag_crawler/crawler.py
insta_hashtag_crawler-0.0.4.dist-info/LICENSE
insta_hashtag_crawler-0.0.4.dist-info/METADATA
insta_hashtag_crawler-0.0.4.dist-info/WHEEL
insta_hashtag_crawler-0.0.4.dist-info/entry_points.txt
insta_hashtag_crawler-0.0.4.dist-info/top_level.txt
insta_hashtag_crawler-0.0.4.dist-info/RECORD
