Metadata-Version: 2.1
Name: insta-hashtag-crawler
Version: 0.0.4
Summary: A gevent-based simple instagram hashtag crawler
Home-page: https://github.com/point1304/insta-hashtag-crawler
Author: K.S. Yim
Author-email: point1304@gmail.com
License: UNKNOWN
Platform: UNKNOWN
Classifier: Programming Language :: Python :: 3
Classifier: License :: OSI Approved :: MIT License
Classifier: Operating System :: OS Independent
Requires-Python: >=3.6
Requires-Dist: gevent (>=1.4.0)
Requires-Dist: requests (>=2.22.0)
